typetree/__init__.py
typetree/ico.py
typetree/py.typed
typetree/typetree.py
typetree/viewer.py
typetree/icons/icon.ico
typetree/icons/minus.ico
typetree/icons/plus.ico
typetree-0.1.7.dist-info/LICENSE.txt
typetree-0.1.7.dist-info/METADATA
typetree-0.1.7.dist-info/WHEEL
typetree-0.1.7.dist-info/top_level.txt
typetree-0.1.7.dist-info/RECORD
