Metadata-Version: 2.1
Name: typetree
Version: 0.1.7
Summary: Tree views of object structures recursively grouped by type.
Author: Hugo Spinelli
License: MIT No Attribution
Project-URL: Source, https://github.com/hugospinelli/typetree
Project-URL: Bug Tracker, https://github.com/hugospinelli/typetree/issues
Project-URL: Documentation, https://typetree.readthedocs.io
Classifier: Programming Language :: Python :: 3.10
Classifier: License :: OSI Approved :: MIT No Attribution License (MIT-0)
Classifier: Topic :: Scientific/Engineering :: Visualization
Requires-Python: >=3.10
License-File: LICENSE.txt
Provides-Extra: clipboard
Requires-Dist: pyperclip (>=1.8.2) ; extra == 'clipboard'
